{"type":"Sprite","props":{"y":0,"x":0,"width":50,"var":"Bullet","presetID":1,"pivotY":25,"pivotX":25,"name":"Bullet","isPresetRoot":true,"height":50},"compId":12,"child":[{"type":"Image","props":{"width":50,"skin":"Frame/UI/ui_circle_c_008.png","presetID":2,"name":"Pic","height":50},"compId":13},{"type":"Script","props":{"width":50,"presetID":3,"label":"bullet","isSensor":true,"height":50,"runtime":"laya.physics.BoxCollider"},"compId":14},{"type":"Script","props":{"presetID":4,"gravityScale":0,"bullet":true,"allowSleep":false,"runtime":"laya.physics.RigidBody"},"compId":15}],"loadList":["Frame/UI/ui_circle_c_008.png"],"loadList3D":[]}